rpyc/__init__.py
rpyc/version.py
rpyc/cli/__init__.py
rpyc/cli/rpyc_classic.py
rpyc/cli/rpyc_registry.py
rpyc/core/__init__.py
rpyc/core/async.py
rpyc/core/async_.py
rpyc/core/brine.py
rpyc/core/channel.py
rpyc/core/consts.py
rpyc/core/netref.py
rpyc/core/protocol.py
rpyc/core/reactor.py
rpyc/core/service.py
rpyc/core/stream.py
rpyc/core/vinegar.py
rpyc/lib/__init__.py
rpyc/lib/colls.py
rpyc/lib/compat.py
rpyc/utils/__init__.py
rpyc/utils/authenticators.py
rpyc/utils/classic.py
rpyc/utils/factory.py
rpyc/utils/helpers.py
rpyc/utils/registry.py
rpyc/utils/server.py
rpyc/utils/teleportation.py
rpyc/utils/zerodeploy.py
rpyc-5.2.2.dist-info/METADATA
rpyc-5.2.2.dist-info/WHEEL
rpyc-5.2.2.dist-info/entry_points.txt
rpyc-5.2.2.dist-info/licenses/LICENSE
rpyc-5.2.2.dist-info/RECORD
