Metadata-Version: 2.1
Name: rpyc
Version: 5.2.2
Summary: Remote Python Call (RPyC) is a transparent and symmetric distributed computing library
Project-URL: Homepage, https://rpyc.readthedocs.org
Project-URL: Source, https://github.com/tomerfiliba-org/rpyc
Author-email: Tomer Filiba <tomerfiliba@gmail.com>, James Stronz <comrumino@archstrike.org>
Classifier: Development Status :: 5 - Production/Stable
Classifier: Intended Audience :: Developers
Classifier: Intended Audience :: System Administrators
Classifier: License :: OSI Approved :: MIT License
Classifier: Operating System :: OS Independent
Classifier: Programming Language :: Python :: 3
Classifier: Programming Language :: Python :: 3.10
Classifier: Programming Language :: Python :: 3.7
Classifier: Programming Language :: Python :: 3.8
Classifier: Programming Language :: Python :: 3.9
Classifier: Topic :: Internet
Classifier: Topic :: Software Development :: Libraries :: Python Modules
Classifier: Topic :: Software Development :: Object Brokering
Classifier: Topic :: Software Development :: Testing
Classifier: Topic :: System :: Clustering
Classifier: Topic :: System :: Distributed Computing
Classifier: Topic :: System :: Monitoring
Classifier: Topic :: System :: Networking
Classifier: Topic :: System :: Systems Administration
Requires-Python: >=3.7
Requires-Dist: plumbum
